{
  "experience_level": "INTERMEDIATE",
  "language_preference": "EN",
  "units": "metric",
  "known_context": {
    "irrigation_type": null,
    "soil_moisture": "OPTIMAL",
    "soil_type": null,
    "forecast_rain_7d": "20mm"
  },
  "last_questions": [
    "cant you gess the current stage of the crop from y the data you have",
    "since you have gdd and sar and sentinel data you can tell",
    "tell me about gdd in this plot",
    "is it raining today ?",
    "how about soil moisture",
    "how about desease risk ? by zone",
    "how is the plot doing this week ?",
    "how is the plot doing this week ?",
    "whats going on",
    "how are you ?"
  ],
  "last_diagnoses_shown": [],
  "asked_followups": [
    "Have you checked the soil for any signs of compaction or crusting?",
    "What is the current soil type in your field?",
    "What type of irrigation system do you use?",
    "Have you noticed any unusual spots or discoloration in the field recently?",
    "Can you provide the total water applied or received this week from your records?",
    "Do you have any specific weather-related concerns or questions?",
    "What is the current soil type in your field?",
    "What type of irrigation system do you use?",
    "What is the current stage of your crop?",
    "What is the current stage of your crop?",
    "What type of irrigation system do you use?",
    "What is the type of crop you are growing?",
    "When did you plant the crop?",
    "What is the specific crop you are growing?",
    "What is the current stage of your crop?",
    "What type of irrigation system do you use?",
    "What is the specific crop you are growing?",
    "Is it currently raining in your area?",
    "What is the specific soil type in your field?",
    "What is the specific soil type in the most vulnerable zones?",
    "What type of irrigation system do you use in the most vulnerable zones?",
    "What is the specific crop you are growing?",
    "What is the specific soil type in your field?",
    "What is the specific soil type in your field?",
    "What type of irrigation system do you use?",
    "What is the specific crop you are planning to plant?",
    "What is the specific soil type in your field?",
    "What is the specific soil type in your field?",
    "What type of irrigation system do you use?"
  ],
  "open_loops": []
}